drapps/__init__.py
drapps/__main__.py
drapps/create.py
drapps/env.py
drapps/externalshare.py
drapps/logs.py
drapps/ls.py
drapps/publish.py
drapps/terminate.py
drapps/helpers/__init__.py
drapps/helpers/app_projects_functions.py
drapps/helpers/custom_app_sources_functions.py
drapps/helpers/custom_apps_functions.py
drapps/helpers/exceptions.py
drapps/helpers/execution_environments_functions.py
drapps/helpers/handle_dr_response.py
drapps/helpers/runtime_params_functions.py
drapps/helpers/wrappers.py
drapps-11.1.0.data/scripts/drapps
drapps-11.1.0.dist-info/licenses/LICENSE
drapps-11.1.0.dist-info/METADATA
drapps-11.1.0.dist-info/WHEEL
drapps-11.1.0.dist-info/top_level.txt
drapps-11.1.0.dist-info/RECORD
