Metadata-Version: 2.4
Name: drapps
Version: 11.1.0
Summary: CLI client for custom application in Data Robot
Home-page: https://github.com/datarobot/dr-apps
Author: Data Robot
Classifier: Programming Language :: Python
Classifier: Programming Language :: Python :: 3
Classifier: Programming Language :: Python :: 3.9
Classifier: Programming Language :: Python :: 3.10
Classifier: Programming Language :: Python :: 3.11
Classifier: Operating System :: OS Independent
Requires-Python: >=3.9
License-File: LICENSE
Requires-Dist: bson==0.5.10
Requires-Dist: click==8.1.7
Requires-Dist: dateutils==0.6.12
Requires-Dist: requests<2.29,>=2.28
Requires-Dist: requests-toolbelt==1.0.0
Requires-Dist: tabulate==0.9.0
Requires-Dist: pathspec==0.12.1
Requires-Dist: PyYAML==6.0.2
Provides-Extra: test
Requires-Dist: pytest==7.4.3; extra == "test"
Requires-Dist: responses==0.23.1; extra == "test"
Requires-Dist: black==23.12.0; extra == "test"
Requires-Dist: flake8==6.1.0; extra == "test"
Requires-Dist: isort==5.13.2; extra == "test"
Requires-Dist: mypy==1.7.1; extra == "test"
Requires-Dist: types-requests==2.28.11; extra == "test"
Requires-Dist: types-tabulate==0.9.0.20240106; extra == "test"
Requires-Dist: types-python-dateutil==2.8.19.20240106; extra == "test"
Requires-Dist: streamlit==1.40.0; extra == "test"
Requires-Dist: datarobot==3.5.2; extra == "test"
Requires-Dist: plotly==5.24.1; extra == "test"
Requires-Dist: kaleido==0.2.1; extra == "test"
Requires-Dist: tabulate==0.9.0; extra == "test"
Requires-Dist: altair==5.4.1; extra == "test"
Requires-Dist: pillow==11.0.0; extra == "test"
Requires-Dist: wordcloud>=1.9.4; extra == "test"
Dynamic: author
Dynamic: classifier
Dynamic: description
Dynamic: description-content-type
Dynamic: home-page
Dynamic: license-file
Dynamic: provides-extra
Dynamic: requires-dist
Dynamic: requires-python
Dynamic: summary
